pamoveit/__init__.py
pamoveit/lib.py
PaMoveIt-0.0.5.dist-info/METADATA
PaMoveIt-0.0.5.dist-info/WHEEL
PaMoveIt-0.0.5.dist-info/top_level.txt
PaMoveIt-0.0.5.dist-info/RECORD
